<?xml version="1.0" encoding="utf-8" ?>
<dwsync>
<file name="back.png" server="D:/Study/php/" local="131232113438067575" remote="131232113430000000" Dst="0" />
<file name="student.png" server="D:/Study/php/" local="131232113438247699" remote="131232113430000000" Dst="0" />
<file name="team.png" server="D:/Study/php/" local="131232113438337768" remote="131232113430000000" Dst="0" />
<file name="back.png" server="C:/wamp/www" local="131242703599431504" remote="131242703590000000" Dst="0" />
<file name="student.png" server="C:/wamp/www" local="131242703599587750" remote="131242703590000000" Dst="0" />
<file name="team.png" server="C:/wamp/www" local="131242703599587750" remote="131242703590000000" Dst="0" />
<file name="staff.png" server="C:/wamp/www" local="131242703599587750" remote="131242703590000000" Dst="0" />
<file name="teamback.png" server="C:/wamp/www" local="131242293469064450" remote="131242293460000000" Dst="0" />
</dwsync>